{
  "title": "A Showcase for Content-Driven Angular Apps",
  "_type": "page",
  "_embedded": {
    "headline": {
      "text": "A Showcase for Content-Driven Angular Apps",
      "_type": "headline",
      "class": "title",
      "size": "2"
    },
    "slider": {
      "_type": "slider",
      "_embedded": {
        "images": [{
            "src": "https://i.ytimg.com/vi/daIBhj9CgD0/sddefault.jpg",
            "alt": "First image",
            "_type": "slider-image"
          },
          {
            "src": "https://encrypted-tbn0.gstatic.com/images?q=tbn:ANd9GcQ0f40czmYDgsBTuzuGSFGHd1JERL7vuYWIcNCy6DEATaYrRbTh",
            "alt": "First image",
            "_type": "slider-image"
          },
          {
            "src": "http://www.wetpaint.com/wp-content/uploads/2017/06/game-of-thrones-spoilers-entertainment-weekly-640x480-1496352938.jpg",
            "alt": "First image",
            "_type": "slider-image"
          },
          {
            "src": "https://1.bp.blogspot.com/-UwVV9n12OcA/WIN1siiVeXI/AAAAAAAAB_0/WIVpjiL8A0MsKIXeMq6Ye_6-5Zq9KKJUwCLcB/s640/The_BFG_Banner_01.jpg",
            "alt": "First image",
            "_type": "slider-image"
          }
        ]
      }
    },

    "article_0": {
      "title": "Article Title ..",
      "_type": "article",
      "color": "primary",
      "subtitle": "Article subtitle ...",
      "content": "Lorem ipsum dolor sit amet, consectetur adipiscing elit. Proin ornare magna eros, eu pellentesque tortor vestibulum ut. Maecenas non massa sem. Etiam finibus odio quis feugiat facilisis.",
      "_embedded": {
        "banner": {
          "src": "https://static.toiimg.com/thumb/msid-60487209,width-640,resizemode-4/60487209.jpg",
          "alt": "Great banter here",
          "_type": "image",
          "ratio": "4by3"
        }
      }
    },
    "mytiles": {
      "_type": "tiles",
      "_embedded": {
        "nexted_tile": {
          "_type": "tile",
          "orientation": "vertical",
          "_embedded": {
            "nexted_tile2": {
              "_type": "tile",
              "_embedded": {
                "tile_01": {
                  "title": "Article Title ..",
                  "_type": "tile",
                  "orientation": "vertical",
                  "parent": true,
                  "_embedded": {
                    "myarticles_1": [{
                      "title": "Vertical...",
                      "_type": "article",
                      "color": "primary",
                      "subtitle": "Top tile",
                      "content": "Lorem ipsum dolor sit amet, consectetur adipiscing elit. Proin ornare magna eros, eu pellentesque tortor vestibulum ut. Maecenas non massa sem. Etiam finibus odio quis feugiat facilisis."
                    }, {
                      "title": "...tiles",
                      "_type": "article",
                      "color": "warning",
                      "subtitle": "Bottom tile",
                      "content": "Lorem ipsum dolor sit amet, consectetur adipiscing elit. Proin ornare magna eros, eu pellentesque tortor vestibulum ut. Maecenas non massa sem. Etiam finibus odio quis feugiat facilisis."
                    }]
                  }
                },
                "middle_tile": {
                  "_type": "tile",
                  "parent": true,
                  "_embedded": {
                    "article_0": {
                      "title": "Article Title ..",
                      "_type": "article",
                      "color": "info",
                      "subtitle": "Article subtitle ...",
                      "content": "Lorem ipsum dolor sit amet, consectetur adipiscing elit. Proin ornare magna eros, eu pellentesque tortor vestibulum ut. Maecenas non massa sem. Etiam finibus odio quis feugiat facilisis.",
                      "_embedded": {
                        "banner": {
                          "src": "https://bulma.io/images/placeholders/640x480.png",
                          "alt": "Great banter here",
                          "_type": "image"
                        }
                      }
                    }
                  }
                }
              }
            },
            "row_tile": {
              "_type": "tile",
              "parent": true,
              "_embedded": {
                "article_10": {
                  "title": "Wide tile",
                  "_type": "article",
                  "color": "danger",
                  "subtitle": "Aligned with the right tile",
                  "content": "Lorem ipsum dolor sit amet, consectetur adipiscing elit. Proin ornare magna eros, eu pellentesque tortor vestibulum ut. Maecenas non massa sem. Etiam finibus odio quis feugiat facilisis."
                }
              }
            }
          }
        },
        "tall_tile": {
          "_type": "tile",
          "parent": true,
          "_embedded": {
            "tall_article": {
              "title": "Tall Article",
              "_type": "article",
              "color": "success",
              "subtitle": "Article subtitle ...",
              "content": "Lorem ipsum dolor sit amet, consectetur adipiscing elit. Proin ornare magna eros, eu pellentesque tortor vestibulum ut. Maecenas non massa sem. Etiam finibus odio quis feugiat facilisis.Lorem ipsum dolor sit amet, consectetur adipiscing elit. Proin ornare magna eros, eu pellentesque tortor vestibulum ut. Maecenas non massa sem. Etiam finibus odio quis feugiat facilisis.Lorem ipsum dolor sit amet, consectetur adipiscing elit. Proin ornare magna eros, eu pellentesque tortor vestibulum ut. Maecenas non massa sem. Etiam finibus odio quis feugiat facilisis.Lorem ipsum dolor sit amet, consectetur adipiscing elit. Proin ornare magna eros, eu pellentesque tortor vestibulum ut. Maecenas non massa sem. Etiam finibus odio quis feugiat facilisis.Lorem ipsum dolor sit amet, consectetur adipiscing elit. Proin ornare magna eros, eu pellentesque tortor vestibulum ut. Maecenas non massa sem. Etiam finibus odio quis feugiat facilisis.Lorem ipsum dolor sit amet, consectetur adipiscing elit. Proin ornare magna eros, eu pellentesque tortor vestibulum ut. Maecenas non massa sem. Etiam finibus odio quis feugiat facilisis.Lorem ipsum dolor sit amet, consectetur adipiscing elit. Proin ornare magna eros, eu pellentesque tortor vestibulum ut. Maecenas non massa sem. Etiam finibus odio quis feugiat facilisis.Lorem ipsum dolor sit amet, consectetur adipiscing elit. Proin ornare magna eros, eu pellentesque tortor vestibulum ut. Maecenas non massa sem. Etiam finibus odio quis feugiat facilisis.Lorem ipsum dolor sit amet, consectetur adipiscing elit. Proin ornare magna eros, eu pellentesque tortor vestibulum ut. Maecenas non massa sem. Etiam finibus odio quis feugiat facilisis."
            }
          }
        }
      }
    }
  },
  "_links": {
    "self": {
      "href": "content/index.json"
    },
    "gallery": {
      "href": "content/gallery.json"
    },
    "imprint": {
      "href": "content/imprint.json"
    }
  }
}
